[
  {
    "content": "100-200",
    "isBot": false,
    "timestamp": "2025-08-07T04:09:19.395Z"
  },
  {
    "content": "Perfect! Now, what type of watch are you looking for? Classic, modern, sporty, or elegant?",
    "isBot": true,
    "timestamp": "2025-08-07T04:09:19.398Z"
  },
  {
    "content": "100-200",
    "isBot": false,
    "timestamp": "2025-08-07T04:09:26.818Z"
  },
  {
    "content": "Great! Let's find you some elegant watches in that price range. Here are some options for you:\n\n[Guess Ladies Black Gold Tone Analog Watch GW0548L3]\n\n[Michael Kors Diamond Darci Three-Hand Two-Tone Stainless Steel Watch]\n\n[Guess Mens Navy Rose Gold Tone Multi-function Watch GW0571G2]",
    "isBot": true,
    "timestamp": "2025-08-07T04:09:26.819Z"
  }
]